sklift/__init__.py
sklift/datasets/__init__.py
sklift/datasets/datasets.py
sklift/datasets/descr/criteo.rst
sklift/datasets/descr/hillstrom.rst
sklift/datasets/descr/lenta.rst
sklift/datasets/descr/megafon.rst
sklift/datasets/descr/x5.rst
sklift/metrics/__init__.py
sklift/metrics/metrics.py
sklift/models/__init__.py
sklift/models/models.py
sklift/tests/__init__.py
sklift/tests/conftest.py
sklift/tests/test_datasets.py
sklift/tests/test_import.py
sklift/tests/test_metrics.py
sklift/tests/test_models.py
sklift/tests/test_viz.py
sklift/utils/__init__.py
sklift/utils/utils.py
sklift/viz/__init__.py
sklift/viz/base.py
scikit_uplift-0.5.1.dist-info/LICENSE
scikit_uplift-0.5.1.dist-info/METADATA
scikit_uplift-0.5.1.dist-info/WHEEL
scikit_uplift-0.5.1.dist-info/top_level.txt
scikit_uplift-0.5.1.dist-info/RECORD
