Metadata-Version: 2.1
Name: scikit-uplift
Version: 0.5.1
Summary: Classic approaches of Uplift modelling in scikit-learn style in python
Home-page: https://github.com/maks-sh/scikit-uplift
Maintainer: Maksim Shevchenko
Classifier: Programming Language :: Python :: 3
Classifier: Operating System :: OS Independent
Provides-Extra: test
License-File: LICENSE
